channelsmultiplexer/__init__.py
channelsmultiplexer/demultiplexer.py
channelsmultiplexer-0.0.2.dist-info/METADATA
channelsmultiplexer-0.0.2.dist-info/RECORD
channelsmultiplexer-0.0.2.dist-info/WHEEL
channelsmultiplexer-0.0.2.dist-info/top_level.txt
tests/migrations/0001_initial.py
tests/migrations/__init__.py
